pySAR/__init__.py
pySAR/descriptors.py
pySAR/encoding.py
pySAR/evaluate.py
pySAR/globals_.py
pySAR/model.py
pySAR/plots.py
pySAR/pyDSP.py
pySAR/pySAR.py
pySAR/utils.py
pySAR-2.4.2.dist-info/LICENSE
pySAR-2.4.2.dist-info/METADATA
pySAR-2.4.2.dist-info/WHEEL
pySAR-2.4.2.dist-info/top_level.txt
pySAR-2.4.2.dist-info/RECORD
