Metadata-Version: 2.1
Name: pySAR
Version: 2.4.2
Summary: A Python package used to analysis Sequence Activity Relationships (SARs) of protein sequences and their mutants using Machine Learning.
Home-page: https://github.com/amckenna41/pySAR
Author: MIT
Author-email: amckenna41@qub.ac.uk
Maintainer: AJ McKenna
License: MIT
Download-URL: https://github.com/amckenna41/pySAR/archive/refs/heads/main.zip
Keywords: bioinformatics,protein engineering,python,pypi,machine learning,directed evolution,drug discovery,sequence activity relationships,SAR,aaindex,protpy,protein descriptors
Platform: UNKNOWN
Classifier: Development Status :: 5 - Production/Stable
Classifier: Environment :: Console
Classifier: Intended Audience :: Developers
Classifier: Intended Audience :: Science/Research
Classifier: Intended Audience :: Healthcare Industry
Classifier: Intended Audience :: Information Technology
Classifier: License :: OSI Approved :: MIT License
Classifier: Natural Language :: English
Classifier: Programming Language :: Python :: 3.8
Classifier: Programming Language :: Python :: 3.9
Classifier: Programming Language :: Python :: 3.10
Classifier: Programming Language :: Python :: Implementation :: PyPy
Classifier: Programming Language :: Python :: 3 :: Only
Classifier: Topic :: Scientific/Engineering :: Bio-Informatics
Classifier: Topic :: Scientific/Engineering :: Medical Science Apps.
Classifier: Topic :: Scientific/Engineering :: Mathematics
Classifier: Topic :: Software Development :: Libraries :: Python Modules
Requires-Python: >=3.8
License-File: LICENSE
Requires-Dist: numpy
Requires-Dist: pandas
Requires-Dist: scipy
Requires-Dist: delayed
Requires-Dist: scikit-learn
Requires-Dist: matplotlib
Requires-Dist: seaborn
Requires-Dist: tqdm
Requires-Dist: aaindex
Requires-Dist: protpy
Provides-Extra: docs
Requires-Dist: sphinx ; extra == 'docs'
Provides-Extra: test
Requires-Dist: pytest ; extra == 'test'
Requires-Dist: pytest-cov ; extra == 'test'
Requires-Dist: pytest-flake8 ; extra == 'test'
Requires-Dist: pytest-timeout ; extra == 'test'
Provides-Extra: test_suite
Requires-Dist: tests ; extra == 'test_suite'
